gitirods/__init__.py
gitirods/check_point.py
gitirods/main.py
gitirods/project.py
gitirods/util.py
gitirods/iinit/__init__.py
gitirods/iinit/iinit.py
gitirods/iinit/session.py
vsc_gitirods-0.2.dist-info/LICENSE
vsc_gitirods-0.2.dist-info/METADATA
vsc_gitirods-0.2.dist-info/WHEEL
vsc_gitirods-0.2.dist-info/top_level.txt
vsc_gitirods-0.2.dist-info/RECORD
