Metadata-Version: 2.1
Name: vsc-gitirods
Version: 0.2
Summary: git iRODS work flow integration tool in Python
Home-page: https://github.com/hpcleuven/vsc-gitirods
Download-URL: https://pypi.org/project/vsc-gitirods/
Author: ICTS-RDM
Author-email: mustafa.dikmen@kuleuven.be
License: LGPL-3.0 license
Keywords: git,iRODS,gitirods,Python 3,GitPython
License-File: LICENSE
Requires-Dist: python-irodsclient (<=v1.1.1)
Requires-Dist: GitPython
